./.gitignore
./PKG-INFO
./README.md
./gsc_dimensions.json
./gsc_filters.json
./gsc_mcp_server.py
./gsc_metrics.json
./pyproject.toml
google_search_console_mcp-0.2.3.dist-info/METADATA
google_search_console_mcp-0.2.3.dist-info/WHEEL
google_search_console_mcp-0.2.3.dist-info/entry_points.txt
google_search_console_mcp-0.2.3.dist-info/RECORD
