Metadata-Version: 2.4
Name: google-search-console-mcp
Version: 0.2.3
Summary: Connect Google Search Console data to Claude, Cursor and other MCP clients. Query your website's search performance data in natural language.
Project-URL: Homepage, https://github.com/surendranb/google-search-console-mcp
Project-URL: Repository, https://github.com/surendranb/google-search-console-mcp.git
Project-URL: Issues, https://github.com/surendranb/google-search-console-mcp/issues
Author-email: Surendran B <reachsuren@gmail.com>
License-Expression: MIT
Classifier: Development Status :: 4 - Beta
Classifier: Intended Audience :: Developers
Classifier: License :: OSI Approved :: MIT License
Classifier: Programming Language :: Python :: 3
Classifier: Programming Language :: Python :: 3.8
Classifier: Programming Language :: Python :: 3.9
Classifier: Programming Language :: Python :: 3.10
Classifier: Programming Language :: Python :: 3.11
Classifier: Topic :: Software Development :: Libraries :: Python Modules
Requires-Python: >=3.8
Requires-Dist: fastmcp>=0.1.0
Requires-Dist: google-api-python-client>=2.0.0
Requires-Dist: google-auth-httplib2>=0.1.0
Requires-Dist: google-auth-oauthlib>=0.4.0
Requires-Dist: google-auth>=2.0.0
